[
  {
    "id": "role_1",
    "name": "Суперадмин",
    "policyIds": [
      "policy_1",
      "policy_2",
      "policy_3",
      "policy_4",
      "policy_5",
      "policy_6"
    ]
  },
  {
    "id": "role_2",
    "name": "Администратор пользователей",
    "policyIds": [
      "policy_1",
      "policy_4"
    ]
  },
  {
    "id": "role_3",
    "name": "Администратор продуктов",
    "policyIds": [
      "policy_2",
      "policy_5"
    ]
  },
  {
    "id": "role_4",
    "name": "Администратор компаний",
    "policyIds": [
      "policy_3",
      "policy_6"
    ]
  },
  {
    "id": "role_5",
    "name": "Можно просматривать только списки всех сущностей",
    "policyIds": [
      // разрешили весь UI
      "policy_1",
      "policy_2",
      "policy_3",
      // разрешили все API
      "policy_4",
      "policy_5",
      "policy_6",
      // запретили на UI все, кроме просмотра списков
      "policy_8",
      "policy_9",
      "policy_11",
      "policy_12",
      "policy_14",
      "policy_15",
      // запретили все API, кроме получения списков
      "policy_17",
      "policy_18",
      "policy_20",
      "policy_21",
      "policy_23",
      "policy_24"
    ]
  },
  {
    "id": "role_6",
    "name": "Можно просматривать только одного пользователя (своего)",
    "policyIds": [
      // разрешили UI и API для пользователей
      "policy_1",
      "policy_4",
      // запретили на UI список пользователей и поиск
      "policy_7",
      "policy_8",
      // запретили в API получения списка пользователей и поиск
      "policy_16",
      "policy_17"
    ]
  },
  {
    "id": "role_7",
    "name": "Можно просматривать только один продукт (созданный текущим пользователем)",
    "policyIds": [
      // разрешили UI и API для продуктов
      "policy_2",
      "policy_5",
      // запретили на UI список продуктов и поиск
      "policy_10",
      "policy_11",
      // запретили в API получения списка продуктов и поиск
      "policy_19",
      "policy_20"
    ]
  },
  {
    "id": "role_8",
    "name": "Можно просматривать только одну компанию (в которой работаешь)",
    "policyIds": [
      // разрешили UI и API для компаний
      "policy_3",
      "policy_6",
      // запретили на UI список компаний и поиск
      "policy_13",
      "policy_14",
      // запретили в API получения списка компаний и поиск
      "policy_22",
      "policy_23"
    ]
  }
]